[
{ "seq_id" : 271, "qsl_idx" : 16489, "data" : "99030000" },
{ "seq_id" : 272, "qsl_idx" : 8731, "data" : "4A020000" },
{ "seq_id" : 273, "qsl_idx" : 9813, "data" : "47030000" },
{ "seq_id" : 274, "qsl_idx" : 44924, "data" : "1F010000" },
{ "seq_id" : 275, "qsl_idx" : 8888, "data" : "6F010000" },
{ "seq_id" : 276, "qsl_idx" : 5108, "data" : "82010000" },
{ "seq_id" : 277, "qsl_idx" : 20602, "data" : "07030000" },
{ "seq_id" : 278, "qsl_idx" : 22730, "data" : "29000000" },
{ "seq_id" : 279, "qsl_idx" : 9615, "data" : "19000000" },
{ "seq_id" : 280, "qsl_idx" : 36611, "data" : "75010000" },
{ "seq_id" : 281, "qsl_idx" : 5197, "data" : "07010000" },
{ "seq_id" : 282, "qsl_idx" : 18220, "data" : "A9020000" },
{ "seq_id" : 283, "qsl_idx" : 8369, "data" : "70020000" },
{ "seq_id" : 284, "qsl_idx" : 47360, "data" : "D8000000" },
{ "seq_id" : 285, "qsl_idx" : 14180, "data" : "3F000000" },
{ "seq_id" : 286, "qsl_idx" : 49637, "data" : "38010000" },
{ "seq_id" : 287, "qsl_idx" : 39130, "data" : "92030000" },
{ "seq_id" : 288, "qsl_idx" : 45808, "data" : "E6030000" },
{ "seq_id" : 289, "qsl_idx" : 22095, "data" : "E3030000" },
{ "seq_id" : 290, "qsl_idx" : 5343, "data" : "4F010000" },
{ "seq_id" : 0, "qsl_idx" : 34016, "data" : "ED020000" },
{ "seq_id" : 1, "qsl_idx" : 9134, "data" : "8F020000" },
{ "seq_id" : 2, "qsl_idx" : 42967, "data" : "47010000" },
{ "seq_id" : 3, "qsl_idx" : 16106, "data" : "C9030000" },
{ "seq_id" : 4, "qsl_idx" : 15512, "data" : "50000000" },
{ "seq_id" : 5, "qsl_idx" : 47633, "data" : "35020000" },
{ "seq_id" : 6, "qsl_idx" : 26965, "data" : "6C000000" },
{ "seq_id" : 7, "qsl_idx" : 17719, "data" : "C0010000" },
{ "seq_id" : 8, "qsl_idx" : 4014, "data" : "BB020000" },
{ "seq_id" : 9, "qsl_idx" : 17825, "data" : "B0020000" },
{ "seq_id" : 10, "qsl_idx" : 48540, "data" : "FA020000" },
{ "seq_id" : 11, "qsl_idx" : 22309, "data" : "24020000" },
{ "seq_id" : 12, "qsl_idx" : 8751, "data" : "02010000" },
{ "seq_id" : 13, "qsl_idx" : 4508, "data" : "CA020000" },
{ "seq_id" : 14, "qsl_idx" : 1328, "data" : "66000000" },
{ "seq_id" : 15, "qsl_idx" : 39108, "data" : "66010000" },
{ "seq_id" : 16, "qsl_idx" : 36321, "data" : "68030000" },
{ "seq_id" : 17, "qsl_idx" : 4217, "data" : "92030000" },
{ "seq_id" : 18, "qsl_idx" : 48596, "data" : "F6010000" },
{ "seq_id" : 19, "qsl_idx" : 32514, "data" : "9E010000" },
{ "seq_id" : 20, "qsl_idx" : 35982, "data" : "6C030000" },
{ "seq_id" : 21, "qsl_idx" : 45516, "data" : "DC030000" },
{ "seq_id" : 22, "qsl_idx" : 969, "data" : "69000000" },
{ "seq_id" : 23, "qsl_idx" : 45307, "data" : "09020000" },
{ "seq_id" : 24, "qsl_idx" : 48352, "data" : "7A020000" },
{ "seq_id" : 25, "qsl_idx" : 27189, "data" : "52020000" },
{ "seq_id" : 26, "qsl_idx" : 23556, "data" : "C0000000" },
{ "seq_id" : 27, "qsl_idx" : 30698, "data" : "09000000" },
{ "seq_id" : 28, "qsl_idx" : 5457, "data" : "98010000" },
{ "seq_id" : 29, "qsl_idx" : 36917, "data" : "01010000" },
{ "seq_id" : 30, "qsl_idx" : 19329, "data" : "7A030000" },
{ "seq_id" : 31, "qsl_idx" : 38619, "data" : "32000000" },
{ "seq_id" : 32, "qsl_idx" : 36101, "data" : "1E000000" },
{ "seq_id" : 33, "qsl_idx" : 16549, "data" : "23000000" },
{ "seq_id" : 34, "qsl_idx" : 23366, "data" : "78030000" },
{ "seq_id" : 35, "qsl_idx" : 14433, "data" : "06020000" },
{ "seq_id" : 36, "qsl_idx" : 41243, "data" : "B3020000" },
{ "seq_id" : 37, "qsl_idx" : 39490, "data" : "8F020000" },
{ "seq_id" : 38, "qsl_idx" : 39908, "data" : "D6030000" },
{ "seq_id" : 39, "qsl_idx" : 2173, "data" : "7C020000" },
{ "seq_id" : 40, "qsl_idx" : 15840, "data" : "DF020000" },
{ "seq_id" : 41, "qsl_idx" : 35314, "data" : "A0000000" },
{ "seq_id" : 42, "qsl_idx" : 17447, "data" : "F6020000" },
{ "seq_id" : 43, "qsl_idx" : 2991, "data" : "22020000" },
{ "seq_id" : 44, "qsl_idx" : 23030, "data" : "62010000" },
{ "seq_id" : 45, "qsl_idx" : 49119, "data" : "60010000" },
{ "seq_id" : 46, "qsl_idx" : 34113, "data" : "66020000" },
{ "seq_id" : 47, "qsl_idx" : 2307, "data" : "71020000" },
{ "seq_id" : 48, "qsl_idx" : 7941, "data" : "84010000" },
{ "seq_id" : 49, "qsl_idx" : 16514

...

: "18010000" },
{ "seq_id" : 49934, "qsl_idx" : 29010, "data" : "95030000" },
{ "seq_id" : 49935, "qsl_idx" : 26788, "data" : "E4020000" },
{ "seq_id" : 49936, "qsl_idx" : 15558, "data" : "2F020000" },
{ "seq_id" : 49937, "qsl_idx" : 49308, "data" : "C6030000" },
{ "seq_id" : 49938, "qsl_idx" : 44053, "data" : "D9010000" },
{ "seq_id" : 49939, "qsl_idx" : 45696, "data" : "84010000" },
{ "seq_id" : 49940, "qsl_idx" : 24447, "data" : "C8030000" },
{ "seq_id" : 49941, "qsl_idx" : 46743, "data" : "F8020000" },
{ "seq_id" : 49942, "qsl_idx" : 33043, "data" : "59020000" },
{ "seq_id" : 49943, "qsl_idx" : 48361, "data" : "74020000" },
{ "seq_id" : 49944, "qsl_idx" : 30221, "data" : "77010000" },
{ "seq_id" : 49945, "qsl_idx" : 43684, "data" : "66030000" },
{ "seq_id" : 49946, "qsl_idx" : 16259, "data" : "09030000" },
{ "seq_id" : 49947, "qsl_idx" : 9275, "data" : "7A030000" },
{ "seq_id" : 49948, "qsl_idx" : 36904, "data" : "4F030000" },
{ "seq_id" : 49949, "qsl_idx" : 41092, "data" : "F0000000" },
{ "seq_id" : 49950, "qsl_idx" : 46521, "data" : "87010000" },
{ "seq_id" : 49951, "qsl_idx" : 686, "data" : "F4020000" },
{ "seq_id" : 49952, "qsl_idx" : 34782, "data" : "66030000" },
{ "seq_id" : 49953, "qsl_idx" : 20125, "data" : "6E000000" },
{ "seq_id" : 49954, "qsl_idx" : 7662, "data" : "28020000" },
{ "seq_id" : 49955, "qsl_idx" : 28786, "data" : "50030000" },
{ "seq_id" : 49956, "qsl_idx" : 26294, "data" : "A7010000" },
{ "seq_id" : 49957, "qsl_idx" : 24850, "data" : "3E000000" },
{ "seq_id" : 49958, "qsl_idx" : 41918, "data" : "20000000" },
{ "seq_id" : 49959, "qsl_idx" : 28958, "data" : "BF030000" },
{ "seq_id" : 49960, "qsl_idx" : 9477, "data" : "FC000000" },
{ "seq_id" : 49961, "qsl_idx" : 7436, "data" : "20000000" },
{ "seq_id" : 49962, "qsl_idx" : 36038, "data" : "BF000000" },
{ "seq_id" : 49963, "qsl_idx" : 20949, "data" : "4F000000" },
{ "seq_id" : 49964, "qsl_idx" : 5519, "data" : "70030000" },
{ "seq_id" : 49965, "qsl_idx" : 23420, "data" : "70030000" },
{ "seq_id" : 49966, "qsl_idx" : 45025, "data" : "17010000" },
{ "seq_id" : 49967, "qsl_idx" : 35826, "data" : "81030000" },
{ "seq_id" : 49968, "qsl_idx" : 31635, "data" : "D9030000" },
{ "seq_id" : 49969, "qsl_idx" : 7575, "data" : "58000000" },
{ "seq_id" : 49970, "qsl_idx" : 44974, "data" : "09000000" },
{ "seq_id" : 49971, "qsl_idx" : 42488, "data" : "B9020000" },
{ "seq_id" : 49972, "qsl_idx" : 34715, "data" : "6B000000" },
{ "seq_id" : 49973, "qsl_idx" : 9227, "data" : "BC010000" },
{ "seq_id" : 49974, "qsl_idx" : 40481, "data" : "C4010000" },
{ "seq_id" : 49975, "qsl_idx" : 11796, "data" : "D3020000" },
{ "seq_id" : 49976, "qsl_idx" : 40454, "data" : "81000000" },
{ "seq_id" : 49977, "qsl_idx" : 46656, "data" : "B5000000" },
{ "seq_id" : 49978, "qsl_idx" : 30995, "data" : "52020000" },
{ "seq_id" : 49979, "qsl_idx" : 34449, "data" : "38030000" },
{ "seq_id" : 49980, "qsl_idx" : 36849, "data" : "1F000000" },
{ "seq_id" : 49981, "qsl_idx" : 45617, "data" : "EE000000" },
{ "seq_id" : 49982, "qsl_idx" : 2059, "data" : "7E000000" },
{ "seq_id" : 49983, "qsl_idx" : 12803, "data" : "D0030000" },
{ "seq_id" : 49984, "qsl_idx" : 46631, "data" : "16000000" },
{ "seq_id" : 49985, "qsl_idx" : 34371, "data" : "52030000" },
{ "seq_id" : 49986, "qsl_idx" : 35514, "data" : "F7020000" },
{ "seq_id" : 49987, "qsl_idx" : 1258, "data" : "C3010000" },
{ "seq_id" : 49988, "qsl_idx" : 43192, "data" : "6F030000" },
{ "seq_id" : 49989, "qsl_idx" : 28313, "data" : "15020000" },
{ "seq_id" : 49990, "qsl_idx" : 19846, "data" : "44020000" },
{ "seq_id" : 49991, "qsl_idx" : 8268, "data" : "2C020000" },
{ "seq_id" : 49992, "qsl_idx" : 29326, "data" : "55020000" },
{ "seq_id" : 49993, "qsl_idx" : 4828, "data" : "00030000" },
{ "seq_id" : 49994, "qsl_idx" : 38630, "data" : "51010000" },
{ "seq_id" : 49995, "qsl_idx" : 46590, "data" : "00010000" },
{ "seq_id" : 49996, "qsl_idx" : 44789, "data" : "C5030000" },
{ "seq_id" : 49997, "qsl_idx" : 47780, "data" : "06030000" },
{ "seq_id" : 49998, "qsl_idx" : 25033, "data" : "4B020000" },
{ "seq_id" : 49999, "qsl_idx" : 42925, "data" : "09000000" }
]
