[
{ "seq_id" : 128, "qsl_idx" : 20157, "data" : "63010000" },
{ "seq_id" : 129, "qsl_idx" : 34338, "data" : "4D030000" },
{ "seq_id" : 130, "qsl_idx" : 47350, "data" : "DB010000" },
{ "seq_id" : 131, "qsl_idx" : 15938, "data" : "C8020000" },
{ "seq_id" : 132, "qsl_idx" : 33583, "data" : "8D010000" },
{ "seq_id" : 133, "qsl_idx" : 36134, "data" : "4E020000" },
{ "seq_id" : 134, "qsl_idx" : 42261, "data" : "BD020000" },
{ "seq_id" : 135, "qsl_idx" : 14494, "data" : "3C030000" },
{ "seq_id" : 136, "qsl_idx" : 41451, "data" : "45000000" },
{ "seq_id" : 137, "qsl_idx" : 5026, "data" : "DC000000" },
{ "seq_id" : 138, "qsl_idx" : 638, "data" : "40010000" },
{ "seq_id" : 139, "qsl_idx" : 2268, "data" : "9D010000" },
{ "seq_id" : 140, "qsl_idx" : 522, "data" : "27000000" },
{ "seq_id" : 141, "qsl_idx" : 1989, "data" : "E3010000" },
{ "seq_id" : 142, "qsl_idx" : 35249, "data" : "55000000" },
{ "seq_id" : 143, "qsl_idx" : 1802, "data" : "4C030000" },
{ "seq_id" : 144, "qsl_idx" : 23074, "data" : "21030000" },
{ "seq_id" : 145, "qsl_idx" : 34026, "data" : "A6020000" },
{ "seq_id" : 146, "qsl_idx" : 9047, "data" : "4E030000" },
{ "seq_id" : 147, "qsl_idx" : 38032, "data" : "8B010000" },
{ "seq_id" : 148, "qsl_idx" : 33610, "data" : "A6000000" },
{ "seq_id" : 149, "qsl_idx" : 25263, "data" : "4F030000" },
{ "seq_id" : 150, "qsl_idx" : 19426, "data" : "63010000" },
{ "seq_id" : 151, "qsl_idx" : 47482, "data" : "EE020000" },
{ "seq_id" : 152, "qsl_idx" : 29353, "data" : "CA000000" },
{ "seq_id" : 153, "qsl_idx" : 6758, "data" : "90020000" },
{ "seq_id" : 154, "qsl_idx" : 16398, "data" : "1A010000" },
{ "seq_id" : 155, "qsl_idx" : 11470, "data" : "C5030000" },
{ "seq_id" : 156, "qsl_idx" : 21248, "data" : "E6000000" },
{ "seq_id" : 157, "qsl_idx" : 17985, "data" : "49000000" },
{ "seq_id" : 158, "qsl_idx" : 17069, "data" : "50020000" },
{ "seq_id" : 159, "qsl_idx" : 26918, "data" : "4E030000" },
{ "seq_id" : 160, "qsl_idx" : 48875, "data" : "EF010000" },
{ "seq_id" : 161, "qsl_idx" : 26104, "data" : "77030000" },
{ "seq_id" : 162, "qsl_idx" : 9555, "data" : "EF000000" },
{ "seq_id" : 163, "qsl_idx" : 4848, "data" : "38020000" },
{ "seq_id" : 164, "qsl_idx" : 38286, "data" : "31000000" },
{ "seq_id" : 165, "qsl_idx" : 27523, "data" : "64020000" },
{ "seq_id" : 166, "qsl_idx" : 49103, "data" : "2B030000" },
{ "seq_id" : 167, "qsl_idx" : 22165, "data" : "81030000" },
{ "seq_id" : 168, "qsl_idx" : 18970, "data" : "0B010000" },
{ "seq_id" : 169, "qsl_idx" : 32969, "data" : "4F000000" },
{ "seq_id" : 170, "qsl_idx" : 16373, "data" : "C1000000" },
{ "seq_id" : 171, "qsl_idx" : 40181, "data" : "EB010000" },
{ "seq_id" : 172, "qsl_idx" : 36874, "data" : "29020000" },
{ "seq_id" : 173, "qsl_idx" : 22387, "data" : "CB000000" },
{ "seq_id" : 174, "qsl_idx" : 16180, "data" : "34010000" },
{ "seq_id" : 175, "qsl_idx" : 37796, "data" : "A4000000" },
{ "seq_id" : 176, "qsl_idx" : 11560, "data" : "DC020000" },
{ "seq_id" : 177, "qsl_idx" : 49569, "data" : "F2000000" },
{ "seq_id" : 178, "qsl_idx" : 6694, "data" : "AB020000" },
{ "seq_id" : 179, "qsl_idx" : 17879, "data" : "03030000" },
{ "seq_id" : 180, "qsl_idx" : 7621, "data" : "02020000" },
{ "seq_id" : 181, "qsl_idx" : 22064, "data" : "88010000" },
{ "seq_id" : 182, "qsl_idx" : 32212, "data" : "1A030000" },
{ "seq_id" : 183, "qsl_idx" : 30256, "data" : "68010000" },
{ "seq_id" : 184, "qsl_idx" : 24737, "data" : "06030000" },
{ "seq_id" : 185, "qsl_idx" : 47715, "data" : "1E000000" },
{ "seq_id" : 186, "qsl_idx" : 37704, "data" : "04000000" },
{ "seq_id" : 187, "qsl_idx" : 38317, "data" : "B8020000" },
{ "seq_id" : 188, "qsl_idx" : 3540, "data" : "79010000" },
{ "seq_id" : 189, "qsl_idx" : 48287, "data" : "FC000000" },
{ "seq_id" : 190, "qsl_idx" : 2727, "data" : "57030000" },
{ "seq_id" : 191, "qsl_idx" : 25781, "data" : "42000000" },
{ "seq_id" : 640, "qsl_idx" : 17795, "data" : "82000000" },
{ "seq_id" : 641, "qsl_idx" : 13855, "data" : "F2000000" },
{ "seq_id" : 642, "qsl_idx" : 33996, "data" : "B7000000" },
{ "seq_id" : 643, "qsl_idx" : 9592, "data" : "DF020000" },
{ "seq_id" : 644, "qsl_idx" : 3

...

ta" : "BB000000" },
{ "seq_id" : 49614, "qsl_idx" : 8727, "data" : "C8020000" },
{ "seq_id" : 49615, "qsl_idx" : 37491, "data" : "90020000" },
{ "seq_id" : 49616, "qsl_idx" : 129, "data" : "1B010000" },
{ "seq_id" : 49617, "qsl_idx" : 3686, "data" : "5D000000" },
{ "seq_id" : 49618, "qsl_idx" : 46641, "data" : "F9020000" },
{ "seq_id" : 49939, "qsl_idx" : 45696, "data" : "84010000" },
{ "seq_id" : 49940, "qsl_idx" : 24447, "data" : "C8030000" },
{ "seq_id" : 49941, "qsl_idx" : 46743, "data" : "F8020000" },
{ "seq_id" : 49942, "qsl_idx" : 33043, "data" : "59020000" },
{ "seq_id" : 49943, "qsl_idx" : 48361, "data" : "74020000" },
{ "seq_id" : 49944, "qsl_idx" : 30221, "data" : "77010000" },
{ "seq_id" : 49945, "qsl_idx" : 43684, "data" : "66030000" },
{ "seq_id" : 49946, "qsl_idx" : 16259, "data" : "09030000" },
{ "seq_id" : 49947, "qsl_idx" : 9275, "data" : "7A030000" },
{ "seq_id" : 49948, "qsl_idx" : 36904, "data" : "4F030000" },
{ "seq_id" : 49949, "qsl_idx" : 41092, "data" : "F0000000" },
{ "seq_id" : 49950, "qsl_idx" : 46521, "data" : "87010000" },
{ "seq_id" : 49951, "qsl_idx" : 686, "data" : "F4020000" },
{ "seq_id" : 49952, "qsl_idx" : 34782, "data" : "66030000" },
{ "seq_id" : 49953, "qsl_idx" : 20125, "data" : "6E000000" },
{ "seq_id" : 49954, "qsl_idx" : 7662, "data" : "28020000" },
{ "seq_id" : 49955, "qsl_idx" : 28786, "data" : "50030000" },
{ "seq_id" : 49956, "qsl_idx" : 26294, "data" : "A7010000" },
{ "seq_id" : 49957, "qsl_idx" : 24850, "data" : "3E000000" },
{ "seq_id" : 49958, "qsl_idx" : 41918, "data" : "20000000" },
{ "seq_id" : 49959, "qsl_idx" : 28958, "data" : "BF030000" },
{ "seq_id" : 49960, "qsl_idx" : 9477, "data" : "FC000000" },
{ "seq_id" : 49961, "qsl_idx" : 7436, "data" : "20000000" },
{ "seq_id" : 49962, "qsl_idx" : 36038, "data" : "BF000000" },
{ "seq_id" : 49963, "qsl_idx" : 20949, "data" : "4F000000" },
{ "seq_id" : 49964, "qsl_idx" : 5519, "data" : "70030000" },
{ "seq_id" : 49965, "qsl_idx" : 23420, "data" : "70030000" },
{ "seq_id" : 49966, "qsl_idx" : 45025, "data" : "17010000" },
{ "seq_id" : 49967, "qsl_idx" : 35826, "data" : "81030000" },
{ "seq_id" : 49968, "qsl_idx" : 31635, "data" : "D9030000" },
{ "seq_id" : 49969, "qsl_idx" : 7575, "data" : "58000000" },
{ "seq_id" : 49970, "qsl_idx" : 44974, "data" : "09000000" },
{ "seq_id" : 49971, "qsl_idx" : 42488, "data" : "B9020000" },
{ "seq_id" : 49972, "qsl_idx" : 34715, "data" : "6B000000" },
{ "seq_id" : 49973, "qsl_idx" : 9227, "data" : "BC010000" },
{ "seq_id" : 49974, "qsl_idx" : 40481, "data" : "C4010000" },
{ "seq_id" : 49975, "qsl_idx" : 11796, "data" : "D3020000" },
{ "seq_id" : 49976, "qsl_idx" : 40454, "data" : "81000000" },
{ "seq_id" : 49977, "qsl_idx" : 46656, "data" : "B5000000" },
{ "seq_id" : 49978, "qsl_idx" : 30995, "data" : "52020000" },
{ "seq_id" : 49979, "qsl_idx" : 34449, "data" : "38030000" },
{ "seq_id" : 49980, "qsl_idx" : 36849, "data" : "1F000000" },
{ "seq_id" : 49981, "qsl_idx" : 45617, "data" : "EE000000" },
{ "seq_id" : 49982, "qsl_idx" : 2059, "data" : "7E000000" },
{ "seq_id" : 49983, "qsl_idx" : 12803, "data" : "D0030000" },
{ "seq_id" : 49984, "qsl_idx" : 46631, "data" : "16000000" },
{ "seq_id" : 49985, "qsl_idx" : 34371, "data" : "52030000" },
{ "seq_id" : 49986, "qsl_idx" : 35514, "data" : "F7020000" },
{ "seq_id" : 49987, "qsl_idx" : 1258, "data" : "C3010000" },
{ "seq_id" : 49988, "qsl_idx" : 43192, "data" : "6F030000" },
{ "seq_id" : 49989, "qsl_idx" : 28313, "data" : "15020000" },
{ "seq_id" : 49990, "qsl_idx" : 19846, "data" : "44020000" },
{ "seq_id" : 49991, "qsl_idx" : 8268, "data" : "2C020000" },
{ "seq_id" : 49992, "qsl_idx" : 29326, "data" : "55020000" },
{ "seq_id" : 49993, "qsl_idx" : 4828, "data" : "00030000" },
{ "seq_id" : 49994, "qsl_idx" : 38630, "data" : "51010000" },
{ "seq_id" : 49995, "qsl_idx" : 46590, "data" : "00010000" },
{ "seq_id" : 49996, "qsl_idx" : 44789, "data" : "C5030000" },
{ "seq_id" : 49997, "qsl_idx" : 47780, "data" : "06030000" },
{ "seq_id" : 49998, "qsl_idx" : 25033, "data" : "4B020000" },
{ "seq_id" : 49999, "qsl_idx" : 42925, "data" : "09000000" }
]
